{
  "/_app": "pages/_app.js",
  "/api/blog": "pages/api/blog.js",
  "/_error": "pages/_error.js",
  "/api/blog/recent": "pages/api/blog/recent.js",
  "/api/comments/[commentId]": "pages/api/comments/[commentId].js",
  "/api/comments": "pages/api/comments.js",
  "/api": "pages/api.js",
  "/dashboard-swr": "pages/dashboard-swr.html",
  "/dashboard": "pages/dashboard.html",
  "/dashboard/list/comments": "pages/dashboard/list/comments.html",
  "/about-us": "pages/about-us.js",
  "/dashboard/list/albums/[albumId]": "pages/dashboard/list/albums/[albumId].js",
  "/dashboard/list/posts/[postId]": "pages/dashboard/list/posts/[postId].js",
  "/dashboard/list": "pages/dashboard/list.js",
  "/dashboard/list/posts": "pages/dashboard/list/posts.js",
  "/dashboard/list/users/[userId]": "pages/dashboard/list/users/[userId].js",
  "/dashboard/list/users": "pages/dashboard/list/users.js",
  "/404": "pages/404.html",
  "/api/googleapi": "pages/api/googleapi.js",
  "/dashboard/list/albums": "pages/dashboard/list/albums.js",
  "/contact-us": "pages/contact-us.js",
  "/_document": "pages/_document.js",
  "/": "pages/index.js"
}